git_helper/__init__.py
git_helper/__main__.py
git_helper/cli.py
git_helper/config.py
git_helper/console.py
git_helper/directory.py
git_helper/errors.py
git_helper/git.py
git_helper/ssh.py
github_helper_cli-0.1.0.dist-info/licenses/LICENSE.md
neogit_tui/__init__.py
neogit_tui/app.py
neogit_tui/config.py
neogit_tui/git.py
neogit_tui/github.py
github_helper_cli-0.1.0.dist-info/METADATA
github_helper_cli-0.1.0.dist-info/WHEEL
github_helper_cli-0.1.0.dist-info/entry_points.txt
github_helper_cli-0.1.0.dist-info/top_level.txt
github_helper_cli-0.1.0.dist-info/RECORD
