Metadata-Version: 2.4
Name: GitHub-Helper-CLI
Version: 0.1.0
Summary: Interactive command line helper for Git workflows
Author: Christopher Hirschauer
Requires-Python: >=3.11
License-File: LICENSE.md
Dynamic: license-file
